aws_dynamodb_operations/__init__.py
aws_dynamodb_operations/dynamodb.py
aws_dynamodb_operations-0.1.0.dist-info/METADATA
aws_dynamodb_operations-0.1.0.dist-info/WHEEL
aws_dynamodb_operations-0.1.0.dist-info/top_level.txt
aws_dynamodb_operations-0.1.0.dist-info/RECORD
