Metadata-Version: 2.2
Name: aws-dynamodb-operations
Version: 0.1.0
Summary: A Python package for common AWS DynamoDB operations
Home-page: https://github.com/MsiziGCBG/aws-dynamodb-operations
Author: Msizi Gumede
Author-email: msizi@cyberneticbg.com
Classifier: Programming Language :: Python :: 3
Classifier: License :: OSI Approved :: MIT License
Classifier: Operating System :: OS Independent
Requires-Python: >=3.6
Requires-Dist: boto3
Dynamic: author
Dynamic: author-email
Dynamic: classifier
Dynamic: description
Dynamic: description-content-type
Dynamic: home-page
Dynamic: requires-dist
Dynamic: requires-python
Dynamic: summary
